{"name":"build-javascript","namedChunkGroups":{"app":{"name":"app","assets":[{"name":"webpack-runtime-edf05e143739a107a20a.js","size":3519},{"name":"framework-08affa2e144238019603.js","size":141392},{"name":"app-779537a9c191b02e47b0.js","size":67912}],"filteredAssets":0,"assetsSize":212823,"filteredAuxiliaryAssets":3,"auxiliaryAssetsSize":609152},"component---src-pages-404-tsx":{"name":"component---src-pages-404-tsx","assets":[{"name":"component---src-pages-404-tsx-53b5c3636c13e7f322e3.js","size":756}],"filteredAssets":0,"assetsSize":756,"filteredAuxiliaryAssets":1,"auxiliaryAssetsSize":1901},"component---src-pages-index-tsx":{"name":"component---src-pages-index-tsx","assets":[{"name":"framework-08affa2e144238019603.js","size":141392},{"name":"component---src-pages-index-tsx-c111543f66759b5e5afe.js","size":118098}],"filteredAssets":0,"assetsSize":259490,"filteredAuxiliaryAssets":2,"auxiliaryAssetsSize":978882}},"assetsByChunkName":{"app":["webpack-runtime-edf05e143739a107a20a.js","framework-08affa2e144238019603.js","app-779537a9c191b02e47b0.js"],"component---src-pages-404-tsx":["component---src-pages-404-tsx-53b5c3636c13e7f322e3.js"],"component---src-pages-index-tsx":["framework-08affa2e144238019603.js","component---src-pages-index-tsx-c111543f66759b5e5afe.js"]},"childAssetsByChunkName":{}}